README.md
setup.cfg
setup.py
morseme/__init__.py
morseme/morseme.py
morseme.egg-info/PKG-INFO
morseme.egg-info/SOURCES.txt
morseme.egg-info/dependency_links.txt
morseme.egg-info/top_level.txt