Metadata-Version: 1.1
Name: morseme
Version: 0.1.2
Summary: A simple morse to human-readable-text converter
Home-page: https://github.com/hvng/morseme
Author: Hung Nguyen
Author-email: hvngcs@gmail.com
License: MIT
Download-URL: https://github.com/hvng/morseme/releases/download/v0.1.2/morseme-0.1.2.tar.gz
Keywords: morse,morseme
Platform: UNKNOWN
Classifier: Development Status :: 4 - Beta
Classifier: Intended Audience :: Developers
Classifier: Topic :: Software Development :: Build Tools
Classifier: License :: OSI Approved :: MIT License
Classifier: Programming Language :: Python :: 3
